backlinks_plugin/__init__.py
backlinks_plugin/plugin.py
mkdocs_backlinks-0.9.1.dist-info/LICENSE
mkdocs_backlinks-0.9.1.dist-info/METADATA
mkdocs_backlinks-0.9.1.dist-info/WHEEL
mkdocs_backlinks-0.9.1.dist-info/entry_points.txt
mkdocs_backlinks-0.9.1.dist-info/top_level.txt
mkdocs_backlinks-0.9.1.dist-info/RECORD
