Metadata-Version: 2.1
Name: mkdocs-backlinks
Version: 0.9.1
Summary: A MkDocs plugin for adding backlinks to your documentation pages.
Home-page: https://github.com/danodic-dev/mkdocs-backlinks
Author: Danilo Guimarães
Author-email: danilo@danodic.dev
License: MIT
Keywords: mkdocs
Classifier: Development Status :: 4 - Beta
Classifier: Intended Audience :: Developers
Classifier: Intended Audience :: Information Technology
Classifier: Intended Audience :: Science/Research
Classifier: License :: OSI Approved :: MIT License
Classifier: Programming Language :: Python
Classifier: Programming Language :: Python :: 3 :: Only
Classifier: Programming Language :: Python :: 3.7
Classifier: Programming Language :: Python :: 3.8
Classifier: Programming Language :: Python :: 3.9
Classifier: Programming Language :: Python :: 3.10
Classifier: Programming Language :: Python :: 3.11
Requires-Python: >=3.10
License-File: LICENSE
Requires-Dist: mkdocs (>=1.4.2)
Requires-Dist: beautifulsoup4 (>=4.11.1)
